tidy_jcm_materials/__init__.py
tidy_jcm_materials/generate.py
tidy_jcm_materials-0.1.1.dist-info/LICENSE
tidy_jcm_materials-0.1.1.dist-info/WHEEL
tidy_jcm_materials-0.1.1.dist-info/METADATA
tidy_jcm_materials-0.1.1.dist-info/RECORD
